dbrownell_BrythonWebviewTest/ApplicationEntryPoint.py
dbrownell_BrythonWebviewTest/Impl/EntryPointUtils.py
dbrownell_BrythonWebviewTest/Impl/__init__.py
dbrownell_BrythonWebviewTest/LocalServerEntryPoint.py
dbrownell_BrythonWebviewTest/__init__.py
dbrownell_BrythonWebviewTest/py.typed
dbrownell_BrythonWebviewTest/web/Server.py
dbrownell_BrythonWebviewTest/web/__init__.py
dbrownell_BrythonWebviewTest/web/index.jinja2.py
dbrownell_BrythonWebviewTest/web/static/brython.js
dbrownell_BrythonWebviewTest/web/static/brython_stdlib.js
dbrownell_BrythonWebviewTest/web/static/index.html
dbrownell_brythonwebviewtest-0.4.2.dist-info/WHEEL
dbrownell_brythonwebviewtest-0.4.2.dist-info/entry_points.txt
dbrownell_brythonwebviewtest-0.4.2.dist-info/METADATA
dbrownell_brythonwebviewtest-0.4.2.dist-info/RECORD
