Metadata-Version: 2.3
Name: dbrownell-brythonwebviewtest
Version: 0.4.2
Summary: Test for Brython and pywebview integration
Author: David Brownell
Author-email: David Brownell <github@davidbrownell.com>
License: MIT
Classifier: Operating System :: MacOS
Classifier: Operating System :: Microsoft :: Windows
Classifier: Operating System :: POSIX :: Linux
Classifier: Programming Language :: Python
Classifier: Programming Language :: Python :: 3.13
Requires-Dist: dbrownell-common>=0.16.0
Requires-Dist: fastapi[standard]>=0.128.0
Requires-Dist: jinja2>=3.1.6
Requires-Dist: pywebview[ssl]>=6.1
Requires-Dist: typer>=0.21.1
Requires-Dist: uvicorn>=0.40.0
Requires-Python: >=3.13
Project-URL: Homepage, https://github.com/davidbrownell/dbrownell_BrythonWebviewTest
Project-URL: Documentation, https://github.com/davidbrownell/dbrownell_BrythonWebviewTest
Project-URL: Repository, https://github.com/davidbrownell/dbrownell_BrythonWebviewTest
